odoo/addons/geoengine_swisstopo/README.rst
odoo/addons/geoengine_swisstopo/__init__.py
odoo/addons/geoengine_swisstopo/__manifest__.py
odoo/addons/geoengine_swisstopo/geo_view/__init__.py
odoo/addons/geoengine_swisstopo/geo_view/geo_raster_layer.py
odoo/addons/geoengine_swisstopo/geo_view/geo_raster_layer_view.xml
odoo/addons/geoengine_swisstopo/i18n/geoengine_swisstopo.pot
odoo/addons/geoengine_swisstopo/readme/DESCRIPTION.rst
odoo/addons/geoengine_swisstopo/static/description/icon.png
odoo/addons/geoengine_swisstopo/static/description/index.html
odoo/addons/geoengine_swisstopo/static/src/js/.eslintrc
odoo/addons/geoengine_swisstopo/static/src/js/swisstopo_geoengine.js
odoo/addons/geoengine_swisstopo/views/geoengine_swisstopo_view.xml
odoo13_addon_geoengine_swisstopo-13.0.1.0.1.dev6.dist-info/METADATA
odoo13_addon_geoengine_swisstopo-13.0.1.0.1.dev6.dist-info/WHEEL
odoo13_addon_geoengine_swisstopo-13.0.1.0.1.dev6.dist-info/top_level.txt
odoo13_addon_geoengine_swisstopo-13.0.1.0.1.dev6.dist-info/RECORD
